easyrocks/__init__.py
easyrocks/easyrocks.py
easyrocks/utils.py
easyrocks-2.214.0.1.dist-info/LICENSE
easyrocks-2.214.0.1.dist-info/METADATA
easyrocks-2.214.0.1.dist-info/WHEEL
easyrocks-2.214.0.1.dist-info/top_level.txt
easyrocks-2.214.0.1.dist-info/RECORD
